stylelens_crawl/__init__.py
stylelens_crawl/stylens_crawl.py
stylelens_crawl/data/sites/site.csv
stylelens_crawl/services/Cafe24.py
stylelens_crawl/services/DeBow.py
stylelens_crawl/services/DoubleSixGirls.py
stylelens_crawl/services/Gogosing.py
stylelens_crawl/services/Imvely.py
stylelens_crawl/services/MakeShop.py
stylelens_crawl/services/Stylenanda.py
stylelens_crawl/services/__init__.py
stylelens_crawl/util/__init__.py
stylelens_crawl/util/data.py
stylelens_crawl-0.1.105.dist-info/DESCRIPTION.rst
stylelens_crawl-0.1.105.dist-info/METADATA
stylelens_crawl-0.1.105.dist-info/RECORD
stylelens_crawl-0.1.105.dist-info/WHEEL
stylelens_crawl-0.1.105.dist-info/metadata.json
stylelens_crawl-0.1.105.dist-info/top_level.txt
