Metadata-Version: 2.0
Name: stylelens-crawl
Version: 0.1.105
Summary: The Stylens crawler for Python
Home-page: https://github.com/BlueLens/stylelens-crawl
Author: Bluehack
Author-email: devops@bluehack.net
License: MIT
Platform: UNKNOWN
Classifier: License :: OSI Approved :: MIT License
Classifier: Programming Language :: Python
Classifier: Programming Language :: Python :: 3.6
Classifier: Development Status :: 1 - Planning
Requires-Dist: Scrapy (>=1.4)
Requires-Dist: requests (>=2.18.4)
Requires-Dist: beautifulsoup4 (>=4.6.0)
Requires-Dist: js2xml (>=0.3.1)
Requires-Dist: google-api-python-client (==1.6.4)
